jentinkj_s21/__about__.py
jentinkj_s21/__init__.py
jentinkj_s21/s21.py
jentinkj_s21-0.0.17.dist-info/METADATA
jentinkj_s21-0.0.17.dist-info/WHEEL
jentinkj_s21-0.0.17.dist-info/RECORD
