Metadata-Version: 2.1
Name: jentinkj_s21
Version: 0.0.17
Project-URL: Documentation, https://github.com/unknown/hatch-demo#readme
Project-URL: Issues, https://github.com/unknown/hatch-demo/issues
Project-URL: Source, https://github.com/unknown/hatch-demo
Author-email: jentinkj <50716461+jentinkj@users.noreply.github.com>
License: MIT
Classifier: Development Status :: 4 - Beta
Classifier: Programming Language :: Python
Classifier: Programming Language :: Python :: 3.8
Classifier: Programming Language :: Python :: 3.9
Classifier: Programming Language :: Python :: 3.10
Classifier: Programming Language :: Python :: 3.11
Classifier: Programming Language :: Python :: 3.12
Classifier: Programming Language :: Python :: Implementation :: CPython
Classifier: Programming Language :: Python :: Implementation :: PyPy
Requires-Python: >=3.8
Requires-Dist: pandas~=2.0
Requires-Dist: pyodbc~=5.0
Requires-Dist: python-dotenv~=1.0
Requires-Dist: requests~=2.32
Requires-Dist: sqlalchemy~=2.0
